setup.cfg
setup.py
Products/__init__.py
Products.XMLWidgets.egg-info/PKG-INFO
Products.XMLWidgets.egg-info/SOURCES.txt
Products.XMLWidgets.egg-info/dependency_links.txt
Products.XMLWidgets.egg-info/namespace_packages.txt
Products.XMLWidgets.egg-info/not-zip-safe
Products.XMLWidgets.egg-info/requires.txt
Products.XMLWidgets.egg-info/top_level.txt
Products/XMLWidgets/CREDITS.txt
Products/XMLWidgets/EditorService.py
Products/XMLWidgets/HISTORY.txt
Products/XMLWidgets/INSTALL.txt
Products/XMLWidgets/LICENSE.txt
Products/XMLWidgets/README.txt
Products/XMLWidgets/WidgetDOM.py
Products/XMLWidgets/WidgetPathScheme.py
Products/XMLWidgets/WidgetRegistry.py
Products/XMLWidgets/__init__.py
Products/XMLWidgets/helpers.py
Products/XMLWidgets/homepage.html
Products/XMLWidgets/version.txt
Products/XMLWidgets/tests/__init__.py
Products/XMLWidgets/tests/test_EditorCache.py
Products/XMLWidgets/tests/test_EditorService.py
Products/XMLWidgets/tests/test_all.py
Products/XMLWidgets/www/editorServiceAdd.zpt
Products/XMLWidgets/www/editorServiceEditTab.zpt
Products/XMLWidgets/www/editorServiceInfoTab.zpt
Products/XMLWidgets/www/editor_service.gif
Products/XMLWidgets/www/widgetRegistryAdd.zpt
Products/XMLWidgets/www/widgetRegistryInfoTab.zpt
Products/XMLWidgets/www/widget_registry.gif
Products/XMLWidgets/www/widget_service.gif