Metadata-Version: 1.0
Name: Products.XMLWidgets
Version: 0.13.1
Summary: XMLWidgets is a Zope 2 product used to create through the web viewers and editors of ParsedXML content.
Home-page: http://infrae.com/products/silva
Author: Martijn Faassen
Author-email: info@infrae.com
License: BSD
Keywords: xml rendering zope2 parsedxml
Platform: UNKNOWN
Classifier: Framework :: Zope2
Classifier: License :: OSI Approved :: BSD License
Classifier: Programming Language :: Python
Classifier: Topic :: Internet :: WWW/HTTP :: Dynamic Content
Classifier: Topic :: Software Development :: Libraries :: Python Modules
Classifier: Topic :: Software Development :: Widget Sets
Classifier: Topic :: Text Processing :: Markup :: HTML
Classifier: Topic :: Text Processing :: Markup :: XML
